procustodibus_agent/__init__.py
procustodibus_agent/agent.py
procustodibus_agent/api.py
procustodibus_agent/cli.py
procustodibus_agent/cnf.py
procustodibus_agent/connectivity.py
procustodibus_agent/credentials.py
procustodibus_agent/extras.py
procustodibus_agent/ip_route.py
procustodibus_agent/resolve_hostname.py
procustodibus_agent/wg.py
procustodibus_agent/wg_cnf.py
procustodibus_agent/executor/__init__.py
procustodibus_agent/executor/execution.py
procustodibus_agent/executor/sys_cmd.py
procustodibus_agent/mfa/__init__.py
procustodibus_agent/mfa/api.py
procustodibus_agent/mfa/cli.py
procustodibus_agent/windows/__init__.py
procustodibus_agent/windows/cnf.py
procustodibus_agent/windows/service.py
procustodibus_agent/windows/service_config.py
procustodibus_agent-1.10.2.dist-info/METADATA
procustodibus_agent-1.10.2.dist-info/WHEEL
procustodibus_agent-1.10.2.dist-info/entry_points.txt
procustodibus_agent-1.10.2.dist-info/licenses/LICENSE
procustodibus_agent-1.10.2.dist-info/RECORD
