Metadata-Version: 2.4
Name: procustodibus_agent
Version: 1.10.2
Summary: Synchronizes your WireGuard settings with Pro Custodibus.
Project-URL: Homepage, https://www.procustodibus.com/
Project-URL: Changelog, https://docs.procustodibus.com/guide/agents/download/#changelog
Project-URL: Documentation, https://docs.procustodibus.com/guide/agents/run/
Project-URL: Source, https://git.sr.ht/~arx10/procustodibus-agent
Project-URL: Tracker, https://todo.sr.ht/~arx10/procustodibus-agent
Author-email: Arcem Tene <dev@arcemtene.com>
License: The MIT License
License-File: LICENSE
Classifier: Development Status :: 5 - Production/Stable
Classifier: Intended Audience :: System Administrators
Classifier: License :: OSI Approved :: MIT License
Classifier: Programming Language :: Python :: 3.8
Classifier: Programming Language :: Python :: 3.9
Classifier: Programming Language :: Python :: 3.10
Classifier: Programming Language :: Python :: 3.11
Classifier: Programming Language :: Python :: 3.12
Classifier: Programming Language :: Python :: 3.13
Classifier: Topic :: System :: Networking :: Monitoring
Requires-Python: >=3.6.2
Requires-Dist: dnspython~=2.2
Requires-Dist: docopt-ng~=0.7
Requires-Dist: importlib-metadata>=4.8.3
Requires-Dist: inflection~=0.5
Requires-Dist: pynacl~=1.5
Requires-Dist: pywin32~=306.0; sys_platform == 'win32'
Requires-Dist: requests~=2.27
Requires-Dist: tabulate~=0.8
